libname/RobloxAPIACCESS.py
libname/__init__.py
RobloxAPIACCESS-0.0.2.dist-info/METADATA
RobloxAPIACCESS-0.0.2.dist-info/WHEEL
RobloxAPIACCESS-0.0.2.dist-info/top_level.txt
RobloxAPIACCESS-0.0.2.dist-info/RECORD
