Metadata-Version: 2.1
Name: RobloxAPIACCESS
Version: 0.0.2
Summary: RobloxAPI Access
Home-page: UNKNOWN
Author: Aristal-Development
Author-email: yqxrkru@valanides.com
License: UNKNOWN
Keywords: python
Platform: UNKNOWN
Classifier: Development Status :: 1 - Planning
Classifier: Intended Audience :: Developers
Classifier: Programming Language :: Python :: 3
Classifier: Operating System :: Unix
Classifier: Operating System :: MacOS :: MacOS X
Classifier: Operating System :: Microsoft :: Windows
Requires-Dist: requests
Requires-Dist: psutil
Requires-Dist: browser-cookie3
Requires-Dist: cryptography
Requires-Dist: pycryptodome
